app/__init__.py
app/config.py
app/forms.py
app/models.py
app/routes.py
fruitbiz_app-0.1.0.dist-info/METADATA
fruitbiz_app-0.1.0.dist-info/WHEEL
fruitbiz_app-0.1.0.dist-info/entry_points.txt
fruitbiz_app-0.1.0.dist-info/top_level.txt
fruitbiz_app-0.1.0.dist-info/RECORD
