Metadata-Version: 2.4
Name: fruitbiz-app
Version: 0.1.0
Summary: A business-focused Flask web application
Author: Manan Shah
Author-email: mananshah256462@gmail.com
Classifier: Programming Language :: Python :: 3
Classifier: Framework :: Flask
Classifier: License :: OSI Approved :: MIT License
Requires-Python: >=3.6
Requires-Dist: Flask>=2.0
Requires-Dist: Flask-SQLAlchemy
Dynamic: author
Dynamic: author-email
Dynamic: classifier
Dynamic: requires-dist
Dynamic: requires-python
Dynamic: summary
